spiderocr/__init__.py
spiderocr/main.py
spiderocr-0.0.1.dist-info/LICENSE
spiderocr-0.0.1.dist-info/METADATA
spiderocr-0.0.1.dist-info/WHEEL
spiderocr-0.0.1.dist-info/top_level.txt
spiderocr-0.0.1.dist-info/RECORD
