Metadata-Version: 2.1
Name: spiderOcr
Version: 0.0.1
Summary: An Util for python packaging.
Keywords: spider,ocr
License-File: LICENSE
